ecs_task_run/__init__.py
ecs_task_run/client.py
ecs_task_run-0.0.3.dist-info/METADATA
ecs_task_run-0.0.3.dist-info/RECORD
ecs_task_run-0.0.3.dist-info/WHEEL
ecs_task_run-0.0.3.dist-info/entry_points.txt
ecs_task_run-0.0.3.dist-info/top_level.txt
