Metadata-Version: 2.1
Name: ecs-task-run
Version: 0.0.3
Summary: ECS Task Definition run
Home-page: https://github.com/creditas/ecs-task-run
Author: Aurelio Saraiva
Author-email: aurelio.saraiva@creditas.com.br
License: UNKNOWN
Platform: UNKNOWN
Classifier: Programming Language :: Python :: 3
Classifier: License :: OSI Approved :: MIT License
Classifier: Operating System :: OS Independent
Requires-Dist: boto3
